spaceship_api/__init__.py
spaceship_api/client.py
spaceship_api/dns_records_types.py
spaceship_api_client-0.1.0.dist-info/entry_points.txt
spaceship_api_client-0.1.0.dist-info/METADATA
spaceship_api_client-0.1.0.dist-info/WHEEL
spaceship_api_client-0.1.0.dist-info/RECORD
