Metadata-Version: 2.3
Name: spaceship-api-client
Version: 0.1.0
Summary: API for spaceship
Author: Benjamin Wiessneth
Author-email: b.wiessneth@gmail.com
Requires-Python: >=3.11,<4.0
Classifier: Programming Language :: Python :: 3
Classifier: Programming Language :: Python :: 3.11
Classifier: Programming Language :: Python :: 3.12
Classifier: Programming Language :: Python :: 3.13
Requires-Dist: pytest (>=8.3.4,<9.0.0)
